MANIFEST.in
README.md
VERSION
requirements-dev.txt
requirements.txt
setup.py
cgp_dss_data_loader.egg-info/PKG-INFO
cgp_dss_data_loader.egg-info/SOURCES.txt
cgp_dss_data_loader.egg-info/dependency_links.txt
cgp_dss_data_loader.egg-info/entry_points.txt
cgp_dss_data_loader.egg-info/requires.txt
cgp_dss_data_loader.egg-info/top_level.txt
cgp_dss_data_loader.egg-info/zip-safe
loader/__init__.py
loader/base_loader.py
loader/schemas.py
loader/standard_loader.py
scripts/__init__.py
scripts/cgp_data_loader.py
util/__init__.py