Metadata-Version: 2.1
Name: cgp-dss-data-loader
Version: 1.1.0
Summary: Simple data loader for CGP HCA Data Store
Home-page: https://github.com/DataBiosphere/cgp-dss-data-loader
Author: Jesse Brennan
Author-email: brennan@ucsc.edu
License: Apache License 2.0
Keywords: genomics,metadata,loading,NIHDataCommons
Platform: UNKNOWN
Classifier: Development Status :: 3 - Alpha
Classifier: Intended Audience :: Science/Research
Classifier: License :: OSI Approved :: Apache Software License
Classifier: Natural Language :: English
Classifier: Programming Language :: Python :: 3.6
Classifier: Topic :: Scientific/Engineering :: Bio-Informatics
